hgftp/__init__.py
hgftp-0.1.1.dist-info/WHEEL
hgftp-0.1.1.dist-info/DESCRIPTION.rst
hgftp-0.1.1.dist-info/METADATA
hgftp-0.1.1.dist-info/top_level.txt
hgftp-0.1.1.dist-info/metadata.json
hgftp-0.1.1.dist-info/RECORD
