Metadata-Version: 2.0
Name: hgftp
Version: 0.1.1
Summary: Upload snapshots of a revision to one or more FTP server
Home-page: https://bitbucket.org/jaltek/hgftp
Author: André Klitzing (misery)
Author-email: andre@incubo.de
License: GPLv2+
Keywords: mercurial ftp
Platform: UNKNOWN
Classifier: Development Status :: 3 - Alpha
Classifier: Environment :: Plugins
Classifier: Intended Audience :: Developers
Classifier: License :: OSI Approved :: GNU General Public License v2 or later (GPLv2+)
Classifier: Operating System :: OS Independent
Classifier: Programming Language :: Python :: 2
Classifier: Programming Language :: Python :: 2.7
Classifier: Topic :: Internet :: File Transfer Protocol (FTP)
Classifier: Topic :: Internet :: WWW/HTTP :: Site Management
Classifier: Topic :: Software Development
Requires-Dist: mercurial
